tests/test_smoke.py
tzip/__init__.py
tzip/archiver.py
tzip/tzip.py
tzip/tzip.tcss
tzip-1.0.0.dist-info/licenses/LICENSE
tzip-1.0.0.dist-info/METADATA
tzip-1.0.0.dist-info/WHEEL
tzip-1.0.0.dist-info/entry_points.txt
tzip-1.0.0.dist-info/top_level.txt
tzip-1.0.0.dist-info/RECORD
