Metadata-Version: 2.4
Name: tzip
Version: 1.0.0
Summary: Textual interface for archive files
Author: FakeTruth
License: MIT
Project-URL: Homepage, https://github.com/FakeTruth/tzip
Project-URL: Source, https://github.com/FakeTruth/tzip
Project-URL: BugTracker, https://github.com/FakeTruth/tzip/issues
Keywords: zip,7z,rar,tar,tui,textual
Classifier: License :: OSI Approved :: MIT License
Classifier: Programming Language :: Python :: 3
Classifier: Programming Language :: Python :: 3 :: Only
Classifier: Programming Language :: Python :: 3.8
Classifier: Programming Language :: Python :: 3.9
Classifier: Programming Language :: Python :: 3.10
Classifier: Programming Language :: Python :: 3.11
Classifier: Operating System :: OS Independent
Requires-Python: >=3.8
License-File: LICENSE
Requires-Dist: textual
Requires-Dist: py7zr
Requires-Dist: rarfile
Provides-Extra: dev
Requires-Dist: pytest>=6.0; extra == "dev"
Dynamic: license-file
